django_manolo-2.4.0.dist-info/top_level.txt
django_manolo-2.4.0.dist-info/RECORD
django_manolo-2.4.0.dist-info/WHEEL
django_manolo-2.4.0.dist-info/metadata.json
django_manolo-2.4.0.dist-info/METADATA
django_manolo-2.4.0.dist-info/DESCRIPTION.rst
manolo/urls.py
manolo/__init__.py
manolo/wsgi.py
manolo/templates/index.html
manolo/templates/api.html
manolo/templates/404.html
manolo/templates/base.html
manolo/templates/500.html
manolo/templates/search/search.html
manolo/templates/visitors/index.html
manolo/templates/layout/js.html
manolo/templates/layout/footer.html
manolo/assets/img/json.svg
manolo/assets/img/results_tsv.png
manolo/assets/img/tsv.svg
manolo/assets/img/2014-12-01_portadas.png
manolo/assets/img/results_search.png
manolo/assets/js/scripts.js
manolo/assets/js/highlighter.js
manolo/assets/css/styles.css
manolo/apps/__init__.py
manolo/apps/visitors/urls.py
manolo/apps/visitors/forms.py
manolo/apps/visitors/__init__.py
manolo/apps/visitors/views.py
manolo/apps/visitors/search_indexes.py
manolo/apps/visitors/models.py
manolo/apps/visitors/serializer.py
manolo/apps/visitors/admin.py
manolo/apps/visitors/tests/test_views.py
manolo/apps/visitors/tests/__init__.py
manolo/apps/visitors/migrations/0002_auto_20150123_1322.py
manolo/apps/visitors/migrations/__init__.py
manolo/apps/visitors/migrations/0001_initial.py
manolo/settings/testing.py
manolo/settings/base.py
manolo/settings/__init__.py
manolo/settings/local.py
manolo/settings/production.py
