Metadata-Version: 2.0
Name: django-manolo
Version: 2.4.0
Summary: Buscador de personas que visitan las instituciones del Estado
Home-page: https://github.com/aniversarioperu/django-manolo
Author: aniversarioperu
Author-email: aniversarioperu1@gmail.com
License: BSD
Keywords: django-manolo
Platform: UNKNOWN
Classifier: Development Status :: 2 - Pre-Alpha
Classifier: Framework :: Django
Classifier: Intended Audience :: Developers
Classifier: License :: OSI Approved :: BSD License
Classifier: Natural Language :: Spanish
Classifier: Programming Language :: Python :: 3.4
